q1ram/__init__.py
q1ram/auth.py
q1ram/circuit.py
q1ram/client.py
q1ram/gateway_loader.py
q1ram/q1ram_gates.py
q1ram/queue.py
q1ram/stack.py
q1ram-0.2.11.dist-info/licenses/LICENSE
q1ram-0.2.11.dist-info/METADATA
q1ram-0.2.11.dist-info/WHEEL
q1ram-0.2.11.dist-info/top_level.txt
q1ram-0.2.11.dist-info/RECORD
