Metadata-Version: 2.4
Name: q1ram
Version: 0.2.11
Summary: Q1RAM Python client for interacting with the Quantum RAM API
Home-page: 
Author: Q1RAM
Author-email: quantum1ram@gmail.com
Classifier: Programming Language :: Python :: 3
Classifier: Operating System :: OS Independent
Requires-Python: >=3.7
License-File: LICENSE
Requires-Dist: requests
Requires-Dist: python-dotenv
Requires-Dist: qiskit>=2.0.0
Requires-Dist: requests
Requires-Dist: qiskit_qasm3_import
Requires-Dist: pylatexenc
Requires-Dist: pydantic
Dynamic: author
Dynamic: author-email
Dynamic: classifier
Dynamic: description
Dynamic: description-content-type
Dynamic: license-file
Dynamic: requires-dist
Dynamic: requires-python
Dynamic: summary
